numina_data_client/__init__.py
numina_data_client/client.py
numina_data_client/constants.py
numina_data_client/mutations.py
numina_data_client/queries.py
numina_data_client/utils/__init__.py
numina_data_client/utils/athena.py
numina_data_client/utils/db.py
numina_data_client/utils/frame.py
numina_data_client/utils/homography.py
numina_data_client/utils/img.py
numina_data_client/utils/metrics.py
numina_data_client-0.42.0.dist-info/METADATA
numina_data_client-0.42.0.dist-info/WHEEL
numina_data_client-0.42.0.dist-info/RECORD
