Metadata-Version: 2.1
Name: numina-data-client
Version: 0.42.0
Summary: 
Author: Numina Engineering
Author-email: inquiries@numina.co
Requires-Python: >=3.9,<4.0
Classifier: Programming Language :: Python :: 3
Classifier: Programming Language :: Python :: 3.9
Classifier: Programming Language :: Python :: 3.10
Classifier: Programming Language :: Python :: 3.11
Requires-Dist: Pillow (>=9.2.0,<10.0.0)
Requires-Dist: awswrangler (>=3.0.0,<4.0.0)
Requires-Dist: boto3 (>=1.24.46,<2.0.0)
Requires-Dist: gql (<=3.3.0)
Requires-Dist: matplotlib (>=3.5.2,<4.0.0)
Requires-Dist: numpy (>=1.23.1,<2.0.0)
Requires-Dist: opencv-python-headless (>=4.6.0,<5.0.0)
Requires-Dist: pandas (>=1.4.3,<2.0.0)
Requires-Dist: requests (>=2.28.1,<3.0.0)
Requires-Dist: requests-toolbelt (>=0.9.1,<0.10.0)
Requires-Dist: shapely (>=2.0.0,<3.0.0)
